[
  {
    "name": "trial",
    "pitchSet": {
      "state": "C4",
      "matrix": {
        "D4": [
          "D4",
          "C4"
        ],
        "C4": [
          "C4",
          "E6",
          "C4"
        ],
        "E6": [
          "E6",
          "Fb3",
          "C4"
        ],
        "Fb3": [
          "Fb3",
          "G5",
          "C4"
        ],
        "G5": [
          "G5",
          "D4"
        ]
      }
    },
    "rhythmSet": {
      "state": "4n",
      "matrix": {
        "4n": [
          "4n",
          "8n"
        ],
        "8n": [
          "8n",
          "4n"
        ]
      }
    }
  }
]